LICENSE
undefined/__init__.py
undefined/py.typed
python_undefined-0.0.2.dist-info/LICENSE
python_undefined-0.0.2.dist-info/METADATA
python_undefined-0.0.2.dist-info/WHEEL
python_undefined-0.0.2.dist-info/RECORD
